.gitignore
MANIFEST.in
README.rst
setup.cfg
setup.py
Products/__init__.py
Products.ContentTypeValidator.egg-info/PKG-INFO
Products.ContentTypeValidator.egg-info/SOURCES.txt
Products.ContentTypeValidator.egg-info/dependency_links.txt
Products.ContentTypeValidator.egg-info/entry_points.txt
Products.ContentTypeValidator.egg-info/namespace_packages.txt
Products.ContentTypeValidator.egg-info/not-zip-safe
Products.ContentTypeValidator.egg-info/requires.txt
Products.ContentTypeValidator.egg-info/top_level.txt
Products/ContentTypeValidator/__init__.py
Products/ContentTypeValidator/configure.zcml
Products/ContentTypeValidator/validator.py
Products/ContentTypeValidator/i18n/ContentTypeValidator-plone.pot
Products/ContentTypeValidator/locales/contenttypevalidator.pot
Products/ContentTypeValidator/locales/de/LC_MESSAGES/contenttypevalidator.mo
Products/ContentTypeValidator/locales/es/LC_MESSAGES/contenttypevalidator.mo
Products/ContentTypeValidator/locales/fr/LC_MESSAGES/contenttypevalidator.mo
Products/ContentTypeValidator/tests/__init__.py
Products/ContentTypeValidator/tests/base.py
Products/ContentTypeValidator/tests/test_ContentTypeValidator.py
Products/ContentTypeValidator/tests/test_files/gif_file.gif
Products/ContentTypeValidator/tests/test_files/odt_file.odt
Products/ContentTypeValidator/tests/test_files/txt_file.txt
docs/HISTORY.txt