Metadata-Version: 1.0
Name: Products.ContentTypeValidator
Version: 2.0b4
Summary: Provides a archetypes field validator for content types of files
Home-page: https://github.com/Raptus/Products.ContentTypeValidator
Author: Raptus AG
Author-email: dev@raptus.com
License: GPL
Platform: UNKNOWN
Classifier: Programming Language :: Python
Classifier: Topic :: Software Development :: Libraries :: Python Modules
